Metadata-Version: 2.1
Name: confusion-matrix
Version: 0.1
Summary: scikit-learn confusion matrix
Home-page: https://scikit-learn.org/stable/auto_examples/model_selection/plot_confusion_matrix.html
Author: scikit-learn developers
License: UNKNOWN
Platform: UNKNOWN
